pyYify/__init__.py
pyYify/yify.py
pyrent/__init__.py
pyrent/yify.py
pyrent-1.9.2.dist-info/LICENSE
pyrent-1.9.2.dist-info/METADATA
pyrent-1.9.2.dist-info/WHEEL
pyrent-1.9.2.dist-info/top_level.txt
pyrent-1.9.2.dist-info/RECORD
