Metadata-Version: 2.1
Name: pyrent
Version: 1.9.2
Summary: This Module is used to get the Top seeded torrents at any given time and get the entire movie details and ratings . Its also useful to search for any movie using different parameters and obtain their magnet link or torrent file of any prefered quality.
Home-page: https://github.com/Anthonipples/pyYify
Author: Anthony Lombard
Author-email: anthony.isalive@gmail.com
License: MIT
Keywords: pyrent,torrent-python,movie-torrent,torrent,pyrent,yify torrent,yify download,download yify,yifyer,yifypy,torrent download,movie torrent,movie downloader,movie finder
Platform: UNKNOWN
Classifier: Programming Language :: Python :: 3.2
Classifier: Programming Language :: Python :: 3.3
Classifier: Programming Language :: Python :: 3.4
Requires-Dist: bs4
Requires-Dist: urllib3
Requires-Dist: requests
